odoo/addons/sale_margin_sync/README.rst
odoo/addons/sale_margin_sync/__init__.py
odoo/addons/sale_margin_sync/__manifest__.py
odoo/addons/sale_margin_sync/i18n/sale_margin_sync.pot
odoo/addons/sale_margin_sync/models/__init__.py
odoo/addons/sale_margin_sync/models/stock_move.py
odoo/addons/sale_margin_sync/readme/CONTRIBUTORS.rst
odoo/addons/sale_margin_sync/readme/DESCRIPTION.rst
odoo/addons/sale_margin_sync/static/description/icon.png
odoo/addons/sale_margin_sync/static/description/index.html
odoo/addons/sale_margin_sync/tests/__init__.py
odoo/addons/sale_margin_sync/tests/test_sale_margin_sync.py
odoo11_addon_sale_margin_sync-11.0.1.0.0.99.dev2.dist-info/METADATA
odoo11_addon_sale_margin_sync-11.0.1.0.0.99.dev2.dist-info/WHEEL
odoo11_addon_sale_margin_sync-11.0.1.0.0.99.dev2.dist-info/top_level.txt
odoo11_addon_sale_margin_sync-11.0.1.0.0.99.dev2.dist-info/RECORD
